{
  "generated_at": "2026-03-31T12:11:05.009575",
  "drift_tier": "ELEVATED",
  "norm_drift": 2.007748247643804,
  "top_regime": "taper_vol",
  "top_sim": 30.1,
  "regime_similarity": [
    {
      "name": "taper_vol",
      "desc": "Taper tantrum / China / oil crash",
      "sim": 30.1
    },
    {
      "name": "gfc",
      "desc": "Credit crisis / deleveraging",
      "sim": 17.8
    },
    {
      "name": "rate_hike",
      "desc": "Inflation / Fed hiking / bear",
      "sim": 15.9
    },
    {
      "name": "ai_bull",
      "desc": "AI-led growth / rate cut cycle",
      "sim": 8.7
    },
    {
      "name": "covid",
      "desc": "Crash + V-shaped recovery",
      "sim": 2.3
    }
  ]
}